setup.py
tradeanal/Strategy.py
tradeanal/Strategy1.py
tradeanal/__init__.py
tradeanal/forward.py
tradeanal/helpers.py
tradeanal.egg-info/PKG-INFO
tradeanal.egg-info/SOURCES.txt
tradeanal.egg-info/dependency_links.txt
tradeanal.egg-info/not-zip-safe
tradeanal.egg-info/requires.txt
tradeanal.egg-info/top_level.txt