Metadata-Version: 1.0
Name: tradeanal
Version: 0.2.13
Summary: tradeanal
Home-page: UNKNOWN
Author: cherepanov_max95
Author-email: cherepanov@ku66.ru
License: UNKNOWN
Platform: UNKNOWN
